Wextracto-0.15.1.dist-info/DESCRIPTION.rst
Wextracto-0.15.1.dist-info/METADATA
Wextracto-0.15.1.dist-info/RECORD
Wextracto-0.15.1.dist-info/WHEEL
Wextracto-0.15.1.dist-info/entry_points.txt
Wextracto-0.15.1.dist-info/metadata.json
Wextracto-0.15.1.dist-info/top_level.txt
wex/__init__.py
wex/cache.py
wex/command.py
wex/composed.py
wex/entrypoints.py
wex/etree.py
wex/extractor.py
wex/form.py
wex/ftp.py
wex/htmlstream.py
wex/http.py
wex/http_decoder.py
wex/iterable.py
wex/logging.conf
wex/ncr.py
wex/output.py
wex/phantomjs.py
wex/processpool.py
wex/py2compat.py
wex/pytestplugin.py
wex/readable.py
wex/regex.py
wex/response.py
wex/sitemaps.py
wex/string.py
wex/url.py
wex/value.py
wex/js/bcr.js
wex/js/phantom.js
