Metadata-Version: 2.0
Name: Wextracto
Version: 0.15.1
Summary: Web Data Extraction Library Written in Python
Home-page: https://github.com/eBay/wextracto
Author: Giles Brown
Author-email: gsbrown@ebay.com
License: BSD
Download-URL: https://github.com/eBay/wextracto/tarball/0.15.1
Platform: UNKNOWN
Classifier: Development Status :: 4 - Beta
Classifier: Intended Audience :: Developers
Classifier: Natural Language :: English
Classifier: License :: OSI Approved :: BSD License
Classifier: Programming Language :: Python
Classifier: Programming Language :: Python :: 2.7
Classifier: Programming Language :: Python :: 3
Classifier: Programming Language :: Python :: 3.4
Requires-Dist: cssselect
Requires-Dist: lxml (>=3)
Requires-Dist: publicsuffix (>=1.1)
Requires-Dist: requests
Requires-Dist: six
